{"regions": [{"categoryCode": null, "masterCode": null, "code": "74030004", "name": "74030004"}, {"categoryCode": null, "masterCode": null, "code": "74030005", "name": "74030005"}, {"categoryCode": null, "masterCode": null, "code": "74030006", "name": "74030006"}, {"categoryCode": null, "masterCode": null, "code": "74030007", "name": "74030007"}, {"categoryCode": null, "masterCode": null, "code": "74030008", "name": "74030008"}, {"categoryCode": null, "masterCode": null, "code": "74030009", "name": "74030009"}, {"categoryCode": null, "masterCode": null, "code": "74030010", "name": "74030010"}, {"categoryCode": null, "masterCode": null, "code": "74030011", "name": "74030011"}, {"categoryCode": null, "masterCode": null, "code": "74030012", "name": "74030012"}, {"categoryCode": null, "masterCode": null, "code": "74030013", "name": "74030013"}, {"categoryCode": null, "masterCode": null, "code": "74030014", "name": "74030014"}, {"categoryCode": null, "masterCode": null, "code": "74030015", "name": "74030015"}, {"categoryCode": null, "masterCode": null, "code": "74030016", "name": "74030016"}]}