{"regions": [{"categoryCode": null, "masterCode": null, "code": "74030101", "name": "74030101"}, {"categoryCode": null, "masterCode": null, "code": "74030102", "name": "74030102"}, {"categoryCode": null, "masterCode": null, "code": "74030103", "name": "74030103"}, {"categoryCode": null, "masterCode": null, "code": "74030104", "name": "74030104"}, {"categoryCode": null, "masterCode": null, "code": "74030105", "name": "74030105"}, {"categoryCode": null, "masterCode": null, "code": "74030106", "name": "74030106"}]}